{
  "meta": {
    "description": "Language-indexed operator messages keyed by operator and message id. Variables are resolved by the operator at runtime.",
    "default_language": "en",
    "version": "cemm.operator_messages.v1"
  },
  "en": {
    "remember": {
      "permission_denied_execute": "Permission denied: execution not allowed",
      "permission_denied_storage": "Permission denied: storage not allowed",
      "insufficient_information": "I don't have enough information to store.",
      "question_not_stored": "Questions are not stored as claims.",
      "predicate_missing": "I couldn't determine a predicate for this fact.",
      "stored_claim": "Stored claim: {subject_id} {predicate}"
    }
  }
}
